Twinnppt/__init__.py
Twinnppt/ppt.py
saurabh1811-0.0.1.dist-info/LICENSE
saurabh1811-0.0.1.dist-info/METADATA
saurabh1811-0.0.1.dist-info/WHEEL
saurabh1811-0.0.1.dist-info/top_level.txt
saurabh1811-0.0.1.dist-info/RECORD
